asana/__init__.py
asana/api_client.py
asana/configuration.py
asana/rest.py
asana/api/__init__.py
asana/api/allocations_api.py
asana/api/attachments_api.py
asana/api/audit_log_api_api.py
asana/api/batch_api_api.py
asana/api/custom_field_settings_api.py
asana/api/custom_fields_api.py
asana/api/custom_types_api.py
asana/api/events_api.py
asana/api/exports_api.py
asana/api/goal_relationships_api.py
asana/api/goals_api.py
asana/api/jobs_api.py
asana/api/memberships_api.py
asana/api/organization_exports_api.py
asana/api/portfolio_memberships_api.py
asana/api/portfolios_api.py
asana/api/project_briefs_api.py
asana/api/project_memberships_api.py
asana/api/project_statuses_api.py
asana/api/project_templates_api.py
asana/api/projects_api.py
asana/api/rules_api.py
asana/api/sections_api.py
asana/api/status_updates_api.py
asana/api/stories_api.py
asana/api/tags_api.py
asana/api/task_templates_api.py
asana/api/tasks_api.py
asana/api/team_memberships_api.py
asana/api/teams_api.py
asana/api/time_periods_api.py
asana/api/time_tracking_entries_api.py
asana/api/typeahead_api.py
asana/api/user_task_lists_api.py
asana/api/users_api.py
asana/api/webhooks_api.py
asana/api/workspace_memberships_api.py
asana/api/workspaces_api.py
asana/pagination/__init__.py
asana/pagination/event_iterator.py
asana/pagination/page_iterator.py
asana-5.2.1.dist-info/licenses/LICENSE
build_tests/__init__.py
build_tests/test_projects_api.py
build_tests/test_tasks_api.py
test/__init__.py
test/test_allocations_api.py
test/test_attachments_api.py
test/test_audit_log_api_api.py
test/test_batch_api_api.py
test/test_custom_field_settings_api.py
test/test_custom_fields_api.py
test/test_custom_types_api.py
test/test_events_api.py
test/test_exports_api.py
test/test_goal_relationships_api.py
test/test_goals_api.py
test/test_jobs_api.py
test/test_memberships_api.py
test/test_organization_exports_api.py
test/test_portfolio_memberships_api.py
test/test_portfolios_api.py
test/test_project_briefs_api.py
test/test_project_memberships_api.py
asana-5.2.1.dist-info/METADATA
asana-5.2.1.dist-info/WHEEL
asana-5.2.1.dist-info/top_level.txt
asana-5.2.1.dist-info/RECORD
