Metadata-Version: 2.4
Name: asana
Version: 5.2.1
Summary: Asana
Home-page: http://github.com/asana/python-asana
Author: Asana, Inc
License: MIT
Keywords: asana,Asana
License-File: LICENSE
Requires-Dist: certifi>=2017.4.17
Requires-Dist: python-dateutil>=2.1
Requires-Dist: six>=1.10
Requires-Dist: urllib3>=1.23
Dynamic: author
Dynamic: description
Dynamic: description-content-type
Dynamic: home-page
Dynamic: keywords
Dynamic: license
Dynamic: license-file
Dynamic: requires-dist
Dynamic: summary
